sgf_image_loader/__init__.py
sgf_image_loader/sgf.py
sgf_image_loader-1.0.1.dist-info/METADATA
sgf_image_loader-1.0.1.dist-info/WHEEL
sgf_image_loader-1.0.1.dist-info/top_level.txt
sgf_image_loader-1.0.1.dist-info/RECORD
