Metadata-Version: 2.2
Name: sgf_image_loader
Version: 1.0.1
Summary: A small package to manage loading and saving SGF files
Author-email: KingToot <armorgamesdot@gmail.com>
Project-URL: Homepage, https://simple.king-toot.com/packages/sgf
Project-URL: Documentation, https://simple.king-toot.com/packages/sgf/docs
Project-URL: Repository, https://github.com/KingToot14/Simple-Graphics-Format.git
Project-URL: Issues, https://github.com/KingToot14/Simple-Graphics-Format/issues
Project-URL: Changelog, https://simple.king-toot.com/packages/sgf/changes
Classifier: Programming Language :: Python :: 3
Classifier: Operating System :: OS Independent
Classifier: License :: OSI Approved :: MIT License
Requires-Python: >=3.8
Requires-Dist: numpy>=2.2.3
Requires-Dist: pillow>=11.1.0
